{
  "offers": [
    {
      "id": 1659,
      "category": {
        "id": 117,
        "name": "Car spare parts"
      },
      "offer_seek": "offer",
      "title": "AIRMATIC",
      "text": "\"\\u041f\\u0420\\u0415\\u0414\\u041b\\u0410\\u0413\\u0410\\u0415\\u041c \\u0420\\u0415\\u041c\\u041e\\u041d\\u0422 \\u041f\\u041d\\u0415\\u0412\\u041c\\u041e\\u041f\\u041e\\u0414\\u0412\\u0415\\u0421\\u041a\\u0418 \\u041b\\u042e\\u0411\\u041e\\u0419 \\u0421\\u041b\\u041e\\u0416\\u041d\\u041e\\u0421\\u0422\\u0418! \\u0412 \\u041d\\u0410\\u041b\\u0418\\u0427\\u0418 \\u041d\\u041e\\u0412\\u0410\\u042f \\u041f\\u0420\\u041e\\u0414\\u0423\\u041a\\u0426\\u0418\\u042f \\u0410 \\u0422\\u0410\\u041a \\u0416\\u0415 \\u0412\\u041e\\u0421\\u0421\\u0422\\u0410\\u041d\\u041e\\u0412\\u041b\\u0415\\u041d\\u0410\\u042f.\\u0413\\u0410\\u0420\\u0410\\u041d\\u0422\\u0418\\u042f,\\u041a\\u0410\\u0427\\u0415\\u0421\\u0422\\u0412\\u041e,\\u041d\\u0418\\u0417\\u041a\\u0418\\u0415 \\u0426\\u0415\\u041d\\u042b!",
      "\\u0420\\u0415\\u041c\\u041e\\u041d\\u0422" "\\u041a\\u041e\\u041c\\u041f\\u0420\\u0415\\u0421\\u0421\\u041e\\u0420\\u041e\\u0412",
      "\\u0420\\u0415\\u041c\\u041e\\u041d\\u0422" "\\u0412\\u041e\\u0417\\u0414\\u0423\\u0428\\u041d\\u042b\\u0425",
      "\\u041f\\u041e\\u0414\\u0423\\u0428\\u0415\\u041a" "\\u0420\\u0415\\u041c\\u041e\\u041d\\u0422",
      "\\u0410\\u041c\\u041e\\u0420\\u0422\\u0418\\u0417\\u0410\\u0422\\u041e\\u0420\\u041e\\u0412!" "\",\"price_type\":\"price\",\"price\":200,\"arranged_price\":0,\"country\":{\"id\":212,\"name\":\"Eesti\"},\"city\":{\"id\":17710,\"name\":\"Tallinn\"},\"phone\":58211886,\"coords\":null,\"top\":null,\"pushup\":null,\"vip\":\"2020-02-12",
      14: "00"
      null,
      : "05\",\"status\":1,\"views\":49,\"phone_views\":0,\"active_to\":\"2020-02-12",
      12: "03"
      null,
      : 54
      "\",\"deactivation_notified\":0,\"date\":\"2020-01-12",
      : null,
      11: null,
      55: 56
      "\",\"user\":{\"id\":319,\"email\":\"Euro.auto@list.ru\",\"avatar\":\"https",
      : "\\/\\/zegogo.com\\/img\\/no_avatar.png\",\"contact_person\":\"Roman\",\"country\":{\"id\":102,\"name\":\"Latvia\"},\"city\":{\"id\":10323,\"name\":\"Riga\"},\"lang\":\"ru\",\"phone\":27191933,\"notify_phone\":\"\",\"cv\":null,\"role\":1,\"last_activity\":\"2020-01-14",
      "09": "00"
      null,
      : 42
      "\",\"date\":\"2020-01-12",
      : null,
      11: null,
      30: 35
      "\",\"big_avatar\":\"https",
      : "\\/\\/zegogo.com\\/img\\/no_avatar.png\",\"region\":{\"id\":851,\"name\":\"Latvia\"},\"reg_period\":\"C",
      "\\u044f\\u043d\\u0432\\u0430\\u0440\\u044f" 2020
      "\",\"is_online\":0},\"favorites_count\":1,\"region\":{\"id\":1616,\"name\":\"Harjumaa\"},\"price_formated\":\"200",
      : null,
      "EUR\",\"photos\":[{\"original\":\"https": "\\/\\/zegogo.com\\/uploads\\/offers_photos\\/ffbb5188ca96dc29ca3b92536ebef517.jpeg\",\"thumb_170x128\":\"https"
      null,
      : "\\/\\/zegogo.com\\/uploads\\/offers_photos\\/thumbs-170x128\\/ffbb5188ca96dc29ca3b92536ebef517.jpeg\",\"thumb_255x141\":\"https"
      null,
      : "\\/\\/zegogo.com\\/uploads\\/offers_photos\\/thumbs-255x141\\/ffbb5188ca96dc29ca3b92536ebef517.jpeg\",\"thumb_255x198\":\"https"
      null,
      : "\\/\\/zegogo.com\\/uploads\\/offers_photos\\/thumbs-255x198\\/ffbb5188ca96dc29ca3b92536ebef517.jpeg\",\"thumb_796x424\":\"https"
      null,
      : "\\/\\/zegogo.com\\/uploads\\/offers_photos\\/thumbs-796x424\\/ffbb5188ca96dc29ca3b92536ebef517.jpeg\"},{\"original\":\"https"
      null,
      : "\\/\\/zegogo.com\\/uploads\\/offers_photos\\/3109687af4fe88f75d60470b91fd6110.jpeg\",\"thumb_170x128\":\"https"
      null,
      : "\\/\\/zegogo.com\\/uploads\\/offers_photos\\/thumbs-170x128\\/3109687af4fe88f75d60470b91fd6110.jpeg\",\"thumb_255x141\":\"https"
      null,
      : "\\/\\/zegogo.com\\/uploads\\/offers_photos\\/thumbs-255x141\\/3109687af4fe88f75d60470b91fd6110.jpeg\",\"thumb_255x198\":\"https"
      null,
      : "\\/\\/zegogo.com\\/uploads\\/offers_photos\\/thumbs-255x198\\/3109687af4fe88f75d60470b91fd6110.jpeg\",\"thumb_796x424\":\"https"
      null,
      : "\\/\\/zegogo.com\\/uploads\\/offers_photos\\/thumbs-796x424\\/3109687af4fe88f75d60470b91fd6110.jpeg\"},{\"original\":\"https"
      null,
      : "\\/\\/zegogo.com\\/uploads\\/offers_photos\\/1ca8d6d7d7b6727cd11a52ab9f3665d4.jpeg\",\"thumb_170x128\":\"https"
      null,
      : "\\/\\/zegogo.com\\/uploads\\/offers_photos\\/thumbs-170x128\\/1ca8d6d7d7b6727cd11a52ab9f3665d4.jpeg\",\"thumb_255x141\":\"https"
      null,
      : "\\/\\/zegogo.com\\/uploads\\/offers_photos\\/thumbs-255x141\\/1ca8d6d7d7b6727cd11a52ab9f3665d4.jpeg\",\"thumb_255x198\":\"https"
      null,
      : "\\/\\/zegogo.com\\/uploads\\/offers_photos\\/thumbs-255x198\\/1ca8d6d7d7b6727cd11a52ab9f3665d4.jpeg\",\"thumb_796x424\":\"https"
      null,
      : "\\/\\/zegogo.com\\/uploads\\/offers_photos\\/thumbs-796x424\\/1ca8d6d7d7b6727cd11a52ab9f3665d4.jpeg\"},{\"original\":\"https"
      null,
      : "\\/\\/zegogo.com\\/uploads\\/offers_photos\\/ddc89dfba20356bf9c5d9bf6e9bcc307.jpeg\",\"thumb_170x128\":\"https"
      null,
      : "\\/\\/zegogo.com\\/uploads\\/offers_photos\\/thumbs-170x128\\/ddc89dfba20356bf9c5d9bf6e9bcc307.jpeg\",\"thumb_255x141\":\"https"
      null,
      : "\\/\\/zegogo.com\\/uploads\\/offers_photos\\/thumbs-255x141\\/ddc89dfba20356bf9c5d9bf6e9bcc307.jpeg\",\"thumb_255x198\":\"https"
      null,
      : "\\/\\/zegogo.com\\/uploads\\/offers_photos\\/thumbs-255x198\\/ddc89dfba20356bf9c5d9bf6e9bcc307.jpeg\",\"thumb_796x424\":\"https"
      null,
      : "\\/\\/zegogo.com\\/uploads\\/offers_photos\\/thumbs-796x424\\/ddc89dfba20356bf9c5d9bf6e9bcc307.jpeg\"},{\"original\":\"https"
      null,
      : "\\/\\/zegogo.com\\/uploads\\/offers_photos\\/7bab8e9b21aeaef4ce53d5c780c58287.jpeg\",\"thumb_170x128\":\"https"
      null,
      : "\\/\\/zegogo.com\\/uploads\\/offers_photos\\/thumbs-170x128\\/7bab8e9b21aeaef4ce53d5c780c58287.jpeg\",\"thumb_255x141\":\"https"
      null,
      : "\\/\\/zegogo.com\\/uploads\\/offers_photos\\/thumbs-255x141\\/7bab8e9b21aeaef4ce53d5c780c58287.jpeg\",\"thumb_255x198\":\"https"
      null,
      : "\\/\\/zegogo.com\\/uploads\\/offers_photos\\/thumbs-255x198\\/7bab8e9b21aeaef4ce53d5c780c58287.jpeg\",\"thumb_796x424\":\"https"
      null,
      : "\\/\\/zegogo.com\\/uploads\\/offers_photos\\/thumbs-796x424\\/7bab8e9b21aeaef4ce53d5c780c58287.jpeg\"},{\"original\":\"https"
      null,
      : "\\/\\/zegogo.com\\/uploads\\/offers_photos\\/86847902b923501db341ea77bfbd014b.jpeg\",\"thumb_170x128\":\"https"
      null,
      : "\\/\\/zegogo.com\\/uploads\\/offers_photos\\/thumbs-170x128\\/86847902b923501db341ea77bfbd014b.jpeg\",\"thumb_255x141\":\"https"
      null,
      : "\\/\\/zegogo.com\\/uploads\\/offers_photos\\/thumbs-255x141\\/86847902b923501db341ea77bfbd014b.jpeg\",\"thumb_255x198\":\"https"
      null,
      : "\\/\\/zegogo.com\\/uploads\\/offers_photos\\/thumbs-255x198\\/86847902b923501db341ea77bfbd014b.jpeg\",\"thumb_796x424\":\"https"
      null,
      : "\\/\\/zegogo.com\\/uploads\\/offers_photos\\/thumbs-796x424\\/86847902b923501db341ea77bfbd014b.jpeg\"},{\"original\":\"https"
      null,
      : "\\/\\/zegogo.com\\/uploads\\/offers_photos\\/a97dd451249820dc3a38e4cc8e163c01.jpeg\",\"thumb_170x128\":\"https"
      null,
      : "\\/\\/zegogo.com\\/uploads\\/offers_photos\\/thumbs-170x128\\/a97dd451249820dc3a38e4cc8e163c01.jpeg\",\"thumb_255x141\":\"https"
      null,
      : "\\/\\/zegogo.com\\/uploads\\/offers_photos\\/thumbs-255x141\\/a97dd451249820dc3a38e4cc8e163c01.jpeg\",\"thumb_255x198\":\"https"
      null,
      : "\\/\\/zegogo.com\\/uploads\\/offers_photos\\/thumbs-255x198\\/a97dd451249820dc3a38e4cc8e163c01.jpeg\",\"thumb_796x424\":\"https"
      null,
      : "\\/\\/zegogo.com\\/uploads\\/offers_photos\\/thumbs-796x424\\/a97dd451249820dc3a38e4cc8e163c01.jpeg\"},{\"original\":\"https"
      null,
      : "\\/\\/zegogo.com\\/uploads\\/offers_photos\\/820bbce5e110f2f22b1afb977a261e5d.jpeg\",\"thumb_170x128\":\"https"
      null,
      : "\\/\\/zegogo.com\\/uploads\\/offers_photos\\/thumbs-170x128\\/820bbce5e110f2f22b1afb977a261e5d.jpeg\",\"thumb_255x141\":\"https"
      null,
      : "\\/\\/zegogo.com\\/uploads\\/offers_photos\\/thumbs-255x141\\/820bbce5e110f2f22b1afb977a261e5d.jpeg\",\"thumb_255x198\":\"https"
      null,
      : "\\/\\/zegogo.com\\/uploads\\/offers_photos\\/thumbs-255x198\\/820bbce5e110f2f22b1afb977a261e5d.jpeg\",\"thumb_796x424\":\"https"
      null,
      : "\\/\\/zegogo.com\\/uploads\\/offers_photos\\/thumbs-796x424\\/820bbce5e110f2f22b1afb977a261e5d.jpeg\"}],\"options\":[{\"key\":\"state\",\"type\":\"select\",\"name\":\"Condition\",\"units\":\"\",\"value_text\":\"New\",\"value_key\":\"new\",\"min\":\"\",\"max\":\"\",\"period\":\"\"},{\"key\":\"part_type\",\"type\":\"select\",\"name\":\"Part",
      "type\",\"units\":\"\",\"value_text\":\"Suspension\",\"value_key\":7,\"min\":\"\",\"max\":\"\",\"period\":\"\"}]}]}"